bazaarpy/__init__.py
bazaarpy/bazaar.py
bazaarpy/items.json
bazaarpy-0.1.4.dist-info/LICENSE
bazaarpy-0.1.4.dist-info/METADATA
bazaarpy-0.1.4.dist-info/WHEEL
bazaarpy-0.1.4.dist-info/top_level.txt
bazaarpy-0.1.4.dist-info/RECORD
