Metadata-Version: 2.1
Name: bazaarpy
Version: 0.1.4
Summary: A Python wrapper for the Hypixel Skyblock Bazaar API
Home-page: https://github.com/Puffball101961/bazaar.py
Author: PuffCode
License: GPL-3.0
License-File: LICENSE
Requires-Dist: requests
